nes_py/__init__.py
nes_py/_image_viewer.py
nes_py/_rom.py
nes_py/lib_nes_env.cpython-39-darwin.so
nes_py/nes_env.py
nes_py/app/__init__.py
nes_py/app/cli.py
nes_py/app/play_human.py
nes_py/app/play_random.py
nes_py/wrappers/__init__.py
nes_py/wrappers/joypad_space.py
nes_py-8.2.1.dist-info/LICENSE
nes_py-8.2.1.dist-info/METADATA
nes_py-8.2.1.dist-info/WHEEL
nes_py-8.2.1.dist-info/entry_points.txt
nes_py-8.2.1.dist-info/top_level.txt
nes_py-8.2.1.dist-info/RECORD
