Metadata-Version: 2.1
Name: nes-py
Version: 8.2.1
Summary: An NES Emulator and OpenAI Gym interface
Home-page: https://github.com/Kautenja/nes-py
Author: Christian Kauten
Author-email: kautencreations@gmail.com
License: MIT
Keywords: NES Emulator OpenAI-Gym
Platform: UNKNOWN
Classifier: Development Status :: 5 - Production/Stable
Classifier: Intended Audience :: Developers
Classifier: Intended Audience :: Science/Research
Classifier: License :: OSI Approved :: MIT License
Classifier: Operating System :: MacOS :: MacOS X
Classifier: Operating System :: POSIX :: Linux
Classifier: Operating System :: Microsoft :: Windows
Classifier: Programming Language :: C++
Classifier: Programming Language :: Python :: 3 :: Only
Classifier: Programming Language :: Python :: 3.5
Classifier: Programming Language :: Python :: 3.6
Classifier: Programming Language :: Python :: 3.7
Classifier: Programming Language :: Python :: 3.8
Classifier: Programming Language :: Python :: 3.9
Classifier: Topic :: Games/Entertainment
Classifier: Topic :: Software Development :: Libraries :: Python Modules
Classifier: Topic :: System :: Emulators
License-File: LICENSE
Requires-Dist: gym (>=0.17.2)
Requires-Dist: numpy (>=1.18.5)
Requires-Dist: pyglet (<=1.5.21,>=1.4.0)
Requires-Dist: tqdm (>=4.48.2)
